Workbook

Sheet Tax Summary
B2: PricewaterhouseCoopers Taxation Services Sdn Bhd
B4: Name | F4: : | G4: ='Tax Comp'!C4 -> 0
B5: Tax Reference Number (IG) | F5: : | G5: ='Tax Comp'!C5 -> 0
B6: Year of Assessment | F6: : | G6: 2025
B7: Basis Period | F7: : | G7: 1 January 2025 - 31 December 2025
AQ9: Chargeable Income [RM]
AQ25: ='Tax Comp'!E29 -> 709245.29
B41: Total [RM] | E41: =Data!C14 -> 718245.29 | X41: Total [RM] | AA41: =Data!C18 -> 9000
AC43: Balance of Tax Payable / (Tax Paid in Excess) [RM]
AC48: ='Tax Comp'!E44 -> -0.1
AC55: Tax Payment Due Date
AC60: 46142
B66: Highest Tax Rate | AA66: Effective Tax Rate
B71: ='Tax Comp'!D34 -> 0.28 | AA71: ='Tax Comp'!E36/'Tax Comp'!E29 -> 0.23544548

Sheet Tax Comp
A2: PricewaterhouseCoopers Taxation Services Sdn Bhd
A4: Name | B4: :
A5: Tax Reference Number (IG) | B5: :
A6: Year of Assessment | B6: : | C6: 2025
A7: Basis Period | B7: : | C7: 1 January 2025 - 31 December 2025
A9: INCOME TAX COMPUTATION
E11: RM
A13: Employment Income
A14: Gross salary, wages or leave pay | E14: 518811.03
A15: Bonuses / Director fees | E15: -
A16: Gross tips, perquisites or other allowances | E16: 133.87
A17: Tax allowance (YA 2024) | E17: 165749
A18: Equity income | E18: -
A19: Gratuity | E19: -
A20: Payment in arrears | E20: -
A21: Benefits-in-kind | E21: 19438.98
A22: Value of living accommodation | E22: 14112.41
A23: Refund from unapproved Pension or Provident Fund | E23: -
A24: Compensation for loss of employment | E24: -
A25: Statutory Income from Employment | E25: =SUM(E14:E24) -> 718245.29
A27: (Less): Total Tax Reliefs | E27: -9000
A29: Chargeable Income | E29: =E25+E27 -> 709245.29
A31: TAX LIABILITY
C32: RM | D32: %
A33: Tax on the First | C33: =IF(E29>=2000000,2000000,IF(E29>=600000,600000,IF(E29>=400000,400000,IF(E29>=100000,100000, IF(E29>=70000,70000,IF(E29>=50000,50000,IF(E29>=35000,35000,IF(E29>=20000,20000,IF(E29>=5000,5000,0))))))))) -> 600000 | E33: =IF(C33=2000000,528400,IF(C33=600000,136400,IF(C33=400000,84400,IF(C33=100000,9400, IF(C33=70000,3700,IF(C33=50000,1500,IF(C33=35000,600,IF(C33=20000,150,IF(C33=5000,0,0))))))))) -> 136400
A34: Tax on the Balance | C34: =ROUND(E29-C33,0) -> 109245 | D34: =IF(C33=2000000,0.3,IF(C33=600000,0.28,IF(C33=400000,0.26,IF(C33=100000,0.25, IF(C33=70000,0.19,IF(C33=50000,0.11,IF(C33=35000,0.06,IF(C33=20000,0.03,IF(C33=5000,0.01,0))))))))) -> 0.28 | E34: =C34*D34 -> 30588.6
A36: Tax Payable / (Repayable) | E36: =E33+E34 -> 166988.6
A38: (Less): Rebate (Restricted) | E38: =IF(E29<=35000, -400, 0) -> 0
A39: (Less): Zakat
E40: =SUM(E36:E39) -> 166988.6
A41: (Less): Foreign tax relief claim (bilateral/unilateral)
A42: (Less): Tax paid via Monthly Tax Deduction | E42: -166988.7
A44: BALANCE OF TAX PAYABLE / (TAX PAID IN EXCESS) | E44: =SUM(E40:E42) -> -0.1

Sheet Data
B2: Income | C2: Amount
B3: ='Tax Comp'!A14 -> Gross salary, wages or leave pay | C3: ='Tax Comp'!E14 -> 518811.03
B4: ='Tax Comp'!A15 -> Bonuses / Director fees | C4: ='Tax Comp'!E15 -> -
B5: ='Tax Comp'!A16 -> Gross tips, perquisites or other allowances | C5: ='Tax Comp'!E16 -> 133.87
B6: ='Tax Comp'!A17 -> Tax allowance (YA 2024) | C6: ='Tax Comp'!E17 -> 165749
B7: ='Tax Comp'!A18 -> Equity income | C7: ='Tax Comp'!E18 -> -
B8: ='Tax Comp'!A19 -> Gratuity | C8: ='Tax Comp'!E19 -> -
B9: ='Tax Comp'!A20 -> Payment in arrears | C9: ='Tax Comp'!E20 -> -
B10: ='Tax Comp'!A21 -> Benefits-in-kind | C10: ='Tax Comp'!E21 -> 19438.98
B11: ='Tax Comp'!A22 -> Value of living accommodation | C11: ='Tax Comp'!E22 -> 14112.41
B12: ='Tax Comp'!A23 -> Refund from unapproved Pension or Provident Fund | C12: ='Tax Comp'!E23 -> -
B13: ='Tax Comp'!A24 -> Compensation for loss of employment | C13: ='Tax Comp'!E24 -> -
C14: =SUM(C3:C13) -> 718245.29
B16: Relief type | C16: Claimed Amount | E16: need to key in manually
B17: Self relief | C17: 9000
C18: =SUM(C17:C17) -> 9000
B20: Tax Category | C20: MTD paid | D20: Tax Liability | E20: Balance of Tax Payable / (Tax Paid in Excess)
D21: ='Tax Comp'!E36 -> 166988.6
C22: ='Tax Comp'!E42 -> -166988.7 | E22: ='Tax Comp'!E44 -> -0.1
