Workbook

Sheet Tax Summary
B1: PricewaterhouseCoopers Taxation Services Sdn Bhd
B3: Name | D3: : | E3: ='Tax Comp'!C4 -> 0
B4: Tax Reference Number (IG) | D4: : | E4: ='Tax Comp'!C5 -> 0
B5: Year of Assessment | D5: : | E5: 2025
B6: Basis Period | D6: : | E6: 1 January 2025 - 31 December 2025
O8: Chargeable Income [RM]
O23: ='Tax Comp'!E25 -> 0
O36: Balance of Tax Payable / (Tax Paid in Excess) [RM]
O47: ='Tax Comp'!E37 -> 0
O52: Tax Payment Due Date
O55: 46142
B59: Highest Tax Rate | M59: Effective Tax Rate
B63: ='Tax Comp'!D29 -> 0.3 | M63: ='Tax Comp'!E30/'Tax Comp'!E25 -> #DIV/0!

Sheet Tax Comp
A2: PricewaterhouseCoopers Taxation Services Sdn Bhd
A4: Name | B4: :
A5: Tax Reference Number (IG) | B5: :
A6: Year of Assessment | B6: : | C6: 2025
A7: Basis Period | B7: : | C7: 1 January 2025 - 31 December 2025
A9: INCOME TAX COMPUTATION
E11: RM
A13: Employment Income
A14: Gross salary, wages or leave pay | E14: 0
A15: Bonuses / Director fees | E15: -
A16: Gross tips, perquisites or other allowances | E16: 0
A17: Tax allowance (YA 2024) | E17: 0
A18: Equity income | E18: -
A19: Gratuity | E19: -
A20: Payment in arrears | E20: -
A21: Benefits-in-kind | E21: 0
A22: Value of living accommodation | E22: -
A23: Refund from unapproved Pension or Provident Fund | E23: -
A24: Compensation for loss of employment | E24: -
A25: Chargeable Income | E25: =SUM(E14:E24) -> 0
A27: TAX LIABILITY
C28: RM | D28: %
A29: Tax on | C29: =ROUND(E25,0) -> 0 | D29: 0.3 | E29: =C29*D29 -> 0
A30: Tax Payable / (Repayable) | E30: =E29 -> 0
A32: (Less): Zakat
E33: =SUM(E30:E32) -> 0
A35: (Less): Tax paid via Monthly Tax Deduction | E35: 0
A37: BALANCE OF TAX PAYABLE / (TAX PAID IN EXCESS) | E37: =SUM(E33:E35) -> 0

Sheet Data
B2: Income | C2: Amount
B3: ='Tax Comp'!A14 -> Gross salary, wages or leave pay | C3: ='Tax Comp'!E14 -> 0
B4: ='Tax Comp'!A15 -> Bonuses / Director fees | C4: ='Tax Comp'!E15 -> -
B5: ='Tax Comp'!A16 -> Gross tips, perquisites or other allowances | C5: ='Tax Comp'!E16 -> 0
B6: ='Tax Comp'!A17 -> Tax allowance (YA 2024) | C6: ='Tax Comp'!E17 -> 0
B7: ='Tax Comp'!A18 -> Equity income | C7: ='Tax Comp'!E18 -> -
B8: ='Tax Comp'!A19 -> Gratuity | C8: ='Tax Comp'!E19 -> -
B9: ='Tax Comp'!A20 -> Payment in arrears | C9: ='Tax Comp'!E20 -> -
B10: ='Tax Comp'!A21 -> Benefits-in-kind | C10: ='Tax Comp'!E21 -> 0
B11: ='Tax Comp'!A22 -> Value of living accommodation | C11: ='Tax Comp'!E22 -> -
B12: ='Tax Comp'!A23 -> Refund from unapproved Pension or Provident Fund | C12: ='Tax Comp'!E23 -> -
B13: ='Tax Comp'!A24 -> Compensation for loss of employment | C13: ='Tax Comp'!E24 -> -
C14: =SUM(C3:C13) -> 0
B17: Tax Category | C17: MTD paid | D17: Tax Liability | E17: Balance of Tax Payable / (Tax Paid in Excess)
D18: ='Tax Comp'!E30 -> 0
C19: =-'Tax Comp'!E35 -> 0 | E19: ='Tax Comp'!E37 -> 0
